README
setup.py
bin/nsnitrocmd.py
nsnitro/__init__.py
nsnitro/nsnitro.py
nsnitro/nsutil.py
nsnitro.egg-info/PKG-INFO
nsnitro.egg-info/SOURCES.txt
nsnitro.egg-info/dependency_links.txt
nsnitro.egg-info/pbr.json
nsnitro.egg-info/requires.txt
nsnitro.egg-info/top_level.txt
nsnitro/nsexceptions/__init__.py
nsnitro/nsexceptions/nsexceptions.py
nsnitro/nsresources/__init__.py
nsnitro/nsresources/authenticationldapaction.py
nsnitro/nsresources/authenticationldappolicy.py
nsnitro/nsresources/authenticationtacacsaction.py
nsnitro/nsresources/authenticationtacacspolicy.py
nsnitro/nsresources/nsacl.py
nsnitro/nsresources/nsacls.py
nsnitro/nsresources/nsbaseresource.py
nsnitro/nsresources/nsconfig.py
nsnitro/nsresources/nscspolicy.py
nsnitro/nsresources/nscspolicycspolicylabelbinding.py
nsnitro/nsresources/nscsvserver.py
nsnitro/nsresources/nscsvservercspolicybinding.py
nsnitro/nsresources/nscsvserverresponderpolicybinding.py
nsnitro/nsresources/nscsvserverrewritepolicybinding.py
nsnitro/nsresources/nscsvserverstat.py
nsnitro/nsresources/nsfeature.py
nsnitro/nsresources/nsgslbconfig.py
nsnitro/nsresources/nsgslbservice.py
nsnitro/nsresources/nsgslbvserver.py
nsnitro/nsresources/nsgslbvserverbinding.py
nsnitro/nsresources/nsgslbvserverdomainbinding.py
nsnitro/nsresources/nsgslbvservergslbservicebinding.py
nsnitro/nsresources/nshanode.py
nsnitro/nsresources/nshardware.py
nsnitro/nsresources/nshostname.py
nsnitro/nsresources/nshttpprofile.py
nsnitro/nsresources/nsip.py
nsnitro/nsresources/nsiptunnel.py
nsnitro/nsresources/nslbmonitor.py
nsnitro/nsresources/nslbmonitorservicebinding.py
nsnitro/nsresources/nslbvserver.py
nsnitro/nsresources/nslbvservercsvserverbinding.py
nsnitro/nsresources/nslbvserverrewritepolicybinding.py
nsnitro/nsresources/nslbvserverservicebinding.py
nsnitro/nsresources/nslbvserverservicegroupbinding.py
nsnitro/nsresources/nslbvserverstat.py
nsnitro/nsresources/nspbr.py
nsnitro/nsresources/nspbrs.py
nsnitro/nsresources/nsresponderaction.py
nsnitro/nsresources/nsresponderpolicy.py
nsnitro/nsresources/nsresponderpolicycsvserverbinding.py
nsnitro/nsresources/nsresponderpolicylabel.py
nsnitro/nsresources/nsresponderpolicylabelbinding.py
