Metadata-Version: 1.1
Name: nsnitro
Version: 1.0.35
Summary: A simple library to control Citrix Netscaler 9.2+ with NITRO API.
Home-page: http://pypi.python.org/pypi/nsnitro
Author: Vladimir Lazarenko
Author-email: vllazarenko@ebay.com
License: GPL
Keywords: citrix netscaler nitro api nsnitro
Platform: UNKNOWN
Classifier: Development Status :: 4 - Beta
Classifier: Topic :: Utilities
Classifier: License :: OSI Approved :: Python Software Foundation License
